pytopia/__init__.py
pytopia/api.py
pytopia/cryptopia_api.py
pytopia/pytopia.py
pytopia-1.0.0.dist-info/LICENSE
pytopia-1.0.0.dist-info/METADATA
pytopia-1.0.0.dist-info/WHEEL
pytopia-1.0.0.dist-info/top_level.txt
pytopia-1.0.0.dist-info/RECORD
