Metadata-Version: 2.1
Name: pytopia
Version: 1.0.0
Summary: Wrapper for Cryptopia API
Home-page: https://github.com/alexarnautu/pytopia/
Author: Alexandru Arnautu
Author-email: alex.arnautu96@gmail.com
License: UNKNOWN
Platform: UNKNOWN
Classifier: Programming Language :: Python :: 3
Classifier: License :: OSI Approved :: MIT License
Classifier: Operating System :: OS Independent
